burphttp/__init__.py
burphttp/burphttp.py
burphttp-0.1.7.dist-info/LICENSE
burphttp-0.1.7.dist-info/METADATA
burphttp-0.1.7.dist-info/WHEEL
burphttp-0.1.7.dist-info/top_level.txt
burphttp-0.1.7.dist-info/RECORD
